.gitignore
README.md
__init__.py
requirements.txt
setup.py
jsonAssured/README.md
jsonAssured/__init__.py
jsonAssured/jsonDiff.py
jsonAssured/jsonPathGenerator.py
jsonAssured.egg-info/PKG-INFO
jsonAssured.egg-info/SOURCES.txt
jsonAssured.egg-info/dependency_links.txt
jsonAssured.egg-info/entry_points.txt
jsonAssured.egg-info/requires.txt
jsonAssured.egg-info/top_level.txt
jsonAssured/__pycache__/__init__.cpython-37.pyc
jsonAssured/__pycache__/jsonPathGenerator.cpython-37.pyc
jsonAssured/sample/mapping.yaml
jsonAssured/sample/source.json
jsonAssured/sample/target.json
jsonAssured/sample/target_all.json